{
	"extends": "tslint:recommended",
	"rulesDirectory": [
	"codelyzer"
	],
	"rules": {
		"variable-name": {
			"options": [
				"ban-keywords",
				"check-format",
				"allow-leading-underscore",
				"allow-pascal-case"
			]
		},
		"quotemark": [true, "double"],
		"member-access": [false],
		"ordered-imports": [false],
		"max-line-length": [true, 150],
		"member-ordering": [false],
		"interface-name": [false],
		"arrow-parens": false,
		"object-literal-sort-keys": false,
		"max-classes-per-file": [false],
		"indent": false,
		"array-type": false,
		"deprecation": {
			"severity": "warn"
		},
		"import-blacklist": [
			true,
			"rxjs/Rx"
		],
		"no-consecutive-blank-lines": false,
		"no-console": [
			true,
			"debug",
			"info",
			"time",
			"timeEnd",
			"trace"
		],
		"no-empty": false,
		"no-inferrable-types": [
			true,
			"ignore-params"
		],
		"no-non-null-assertion": true,
		"no-redundant-jsdoc": true,
		"no-switch-case-fall-through": true,
		"no-use-before-declare": true,
		"no-var-requires": false,
		"object-literal-key-quotes": [
			true,
			"as-needed"
		],
		"trailing-comma": false,
		"no-output-on-prefix": true,
		"use-input-property-decorator": true,
		"use-output-property-decorator": true,
		"use-host-property-decorator": true,
		"no-input-rename": true,
		"no-output-rename": true,
		"use-life-cycle-interface": true,
		"use-pipe-transform-interface": true,
		"component-class-suffix": true,
		"directive-class-suffix": true
	}
}
